PIPS/__init__.py
PIPS/OC/__init__.py
PIPS/class_StellarModels/__init__.py
PIPS/class_photdata/__init__.py
PIPS/class_visualize/__init__.py
PIPS/periodogram/__init__.py
PIPS/periodogram/custom/__init__.py
PIPS/periodogram/custom/custom.py
PIPS/periodogram/custom/models/Fourier.py
PIPS/periodogram/custom/models/Gaussian.py
PIPS/periodogram/custom/models/__init__.py
PIPS/periodogram/linalg/__init__.py
PIPS/periodogram/linalg/linalg.py
PIPS/resources/__init__.py
PIPS/resources/filters/__init__.py
PIPS/resources/sample_RRL/__init__.py
PIPS/utils/__init__.py
PIPS/utils/connect_LPP.py
PIPS/utils/get_Temp.py
PIPS/utils/read_filter.py
astroPIPS-0.3b4.dist-info/LICENSE
astroPIPS-0.3b4.dist-info/METADATA
astroPIPS-0.3b4.dist-info/WHEEL
astroPIPS-0.3b4.dist-info/top_level.txt
astroPIPS-0.3b4.dist-info/RECORD
