Metadata-Version: 2.1
Name: astroPIPS
Version: 0.3b4
Summary: Processes photometric data for variable stars
Home-page: https://PIPS.readthedocs.io
Author: Y. Murakami, A. Savel, J. Sunseri, A. Hoffman, Ivan Altunin, Nachiket Girish
Author-email: sterling.astro@berkeley.edu
Maintainer: Y. Murakami
Maintainer-email: sterling.astro@berkeley.edu
License: MIT
Platform: UNKNOWN
Classifier: Development Status :: 4 - Beta
Classifier: Intended Audience :: Developers
Classifier: Intended Audience :: Science/Research
Classifier: Natural Language :: English
Classifier: License :: OSI Approved :: MIT License
Classifier: Programming Language :: Python
Classifier: Programming Language :: Python :: 3.7
Classifier: Programming Language :: Python :: 3.8
Classifier: Topic :: Scientific/Engineering :: Astronomy
Requires-Python: >3.7.0
Requires-Dist: numpy
Requires-Dist: scipy
Requires-Dist: matplotlib
Requires-Dist: astropy
Requires-Dist: numba
Requires-Dist: nbsphinx
Requires-Dist: emcee
Requires-Dist: pandas
